[ { "asset_id" : "6061546331001", "remote" : false, "app_name" : "rtmp://brightcove.fcod.llnwd.net/a500/e1/uds/rtmp/ondemand", "stream_name" : "mp4:2103045685001/2103045685001_6061546331001_6061535078001.mp4&1570694400000&b188100f20a48426aab08c57642ac30d", "codec" : "H264", "container" : "MP4", "encoding_rate" : 1824000, "duration" : 315647, "height" : 540, "width" : 960, "size" : 72139544, "uploaded_at" : "2019-07-19T14:12:35.154Z" }, { "asset_id" : "6061546331001", "remote" : false, "src" : "http://f1.media.brightcove.com/4/2103045685001/2103045685001_6061546331001_6061535078001.mp4?pubId=2103045685001&videoId=6061535078001", "codec" : "H264", "container" : "MP4", "encoding_rate" : 1824000, "duration" : 315647, "height" : 540, "width" : 960, "size" : 72139544, "uploaded_at" : "2019-07-19T14:12:35.154Z" }, { "asset_id" : "6061546331001", "remote" : false, "src" : "https://f1.media.brightcove.com/4/2103045685001/2103045685001_6061546331001_6061535078001.mp4?pubId=2103045685001&videoId=6061535078001", "codec" : "H264", "container" : "MP4", "encoding_rate" : 1824000, "duration" : 315647, "height" : 540, "width" : 960, "size" : 72139544, "uploaded_at" : "2019-07-19T14:12:35.154Z" }, { "asset_id" : "6061546423001", "remote" : false, "app_name" : "rtmp://brightcove.fcod.llnwd.net/a500/e1/uds/rtmp/ondemand", "stream_name" : "mp4:2103045685001/2103045685001_6061546423001_6061535078001.mp4&1570694400000&b188100f20a48426aab08c57642ac30d", "codec" : "H264", "container" : "MP4", "encoding_rate" : 995000, "duration" : 315647, "height" : 360, "width" : 640, "size" : 39372542, "uploaded_at" : "2019-07-19T14:12:26.372Z" }, { "asset_id" : "6061546423001", "remote" : false, "src" : "http://f1.media.brightcove.com/4/2103045685001/2103045685001_6061546423001_6061535078001.mp4?pubId=2103045685001&videoId=6061535078001", "codec" : "H264", "container" : "MP4", "encoding_rate" : 995000, "duration" : 315647, "height" : 360, "width" : 640, "size" : 39372542, "uploaded_at" : "2019-07-19T14:12:26.372Z" }, { "asset_id" : "6061546423001", "remote" : false, "src" : "https://f1.media.brightcove.com/4/2103045685001/2103045685001_6061546423001_6061535078001.mp4?pubId=2103045685001&videoId=6061535078001", "codec" : "H264", "container" : "MP4", "encoding_rate" : 995000, "duration" : 315647, "height" : 360, "width" : 640, "size" : 39372542, "uploaded_at" : "2019-07-19T14:12:26.372Z" }, { "asset_id" : "6061547851001", "remote" : false, "app_name" : "rtmp://brightcove.fcod.llnwd.net/a500/e1/uds/rtmp/ondemand", "stream_name" : "mp4:2103045685001/2103045685001_6061547851001_6061535078001.mp4&1570694400000&b188100f20a48426aab08c57642ac30d", "codec" : "H264", "container" : "MP4", "encoding_rate" : 512000, "duration" : 315647, "height" : 270, "width" : 480, "size" : 20336889, "uploaded_at" : "2019-07-19T14:12:15.319Z" }, { "asset_id" : "6061547851001", "remote" : false, "src" : "http://f1.media.brightcove.com/4/2103045685001/2103045685001_6061547851001_6061535078001.mp4?pubId=2103045685001&videoId=6061535078001", "codec" : "H264", "container" : "MP4", "encoding_rate" : 512000, "duration" : 315647, "height" : 270, "width" : 480, "size" : 20336889, "uploaded_at" : "2019-07-19T14:12:15.319Z" }, { "asset_id" : "6061547851001", "remote" : false, "src" : "https://f1.media.brightcove.com/4/2103045685001/2103045685001_6061547851001_6061535078001.mp4?pubId=2103045685001&videoId=6061535078001", "codec" : "H264", "container" : "MP4", "encoding_rate" : 512000, "duration" : 315647, "height" : 270, "width" : 480, "size" : 20336889, "uploaded_at" : "2019-07-19T14:12:15.319Z" }, { "src" : "http://c.brightcove.com/services/mobile/streaming/index/master.m3u8?videoId=6061535078001&pubId=2103045685001", "type" : "application/x-mpegURL", "container" : "M2TS", "uploaded_at" : "2019-07-19T14:12:37.688Z", "codec" : "H264" }, { "src" : "https://secure.brightcove.com/services/mobile/streaming/index/master.m3u8?videoId=6061535078001&pubId=2103045685001&secure=true", "type" : "application/x-mpegURL", "container" : "M2TS", "uploaded_at" : "2019-07-19T14:12:37.688Z", "codec" : "H264" } ]
